{"documentation":"https://opencagedata.com/api","licenses":[{"name":"see attribution guide","url":"https://opencagedata.com/credits"}],"rate":{"limit":2500,"remaining":2414,"reset":1715299200},"results":[{"annotations":{"DMS":{"lat":"32\u00b0 18' 14.49828'' N","lng":"64\u00b0 45' 22.71096'' W"},"MGRS":"20SLA3464575490","Maidenhead":"FM72oh92fx","Mercator":{"x":-7208639.299,"y":3780452.735},"OSM":{"edit_url":"https://www.openstreetmap.org/edit?relation=1993208#map=17/32.30403/-64.75631","note_url":"https://www.openstreetmap.org/note/new#map=17/32.30403/-64.75631&layers=N","url":"https://www.openstreetmap.org/?mlat=32.30403&mlon=-64.75631#map=17/32.30403/-64.75631"},"UN_M49":{"regions":{"AMERICAS":"019","BM":"060","NORTHERN_AMERICA":"021","WORLD":"001"},"statistical_groupings":["MEDC"]},"callingcode":1,"currency":{"alternate_symbols":["BD$"],"decimal_mark":".","disambiguate_symbol":"BD$","html_entity":"$","iso_code":"BMD","iso_numeric":"060","name":"Bermudian Dollar","smallest_denomination":1,"subunit":"Cent","subunit_to_unit":100,"symbol":"$","symbol_first":1,"thousands_separator":","},"flag":"\ud83c\udde7\ud83c\uddf2","geohash":"dt9zy2vbsehsfgem2ny6","qibla":64.28,"roadinfo":{"drive_on":"left","speed_in":"km/h"},"sun":{"rise":{"apparent":1715246760,"astronomical":1715241240,"civil":1715245200,"nautical":1715243280},"set":{"apparent":1715295900,"astronomical":1715215080,"civil":1715297520,"nautical":1715213040}},"timezone":{"name":"Atlantic/Bermuda","now_in_dst":1,"offset_sec":-10800,"offset_string":"-0300","short_name":"ADT"},"what3words":{"words":"pursue.relaxed.propelled"},"wikidata":"Q23635"},"bounds":{"northeast":{"lat":32.5913693,"lng":-64.4109842},"southwest":{"lat":32.0469651,"lng":-65.1232222}},"components":{"ISO_3166-1_alpha-2":"BM","ISO_3166-1_alpha-3":"BMU","_category":"place","_type":"country","continent":"North America","country":"Bermuda","country_code":"bm"},"confidence":1,"formatted":"Bermuda","geometry":{"lat":32.3040273,"lng":-64.7563086}}],"status":{"code":200,"message":"OK"},"stay_informed":{"blog":"https://blog.opencagedata.com","mastodon":"https://en.osm.town/@opencage"},"thanks":"For using an OpenCage API","timestamp":{"created_http":"Thu, 09 May 2024 15:58:10 GMT","created_unix":1715270290},"total_results":1}