{"documentation":"https://opencagedata.com/api","licenses":[{"name":"see attribution guide","url":"https://opencagedata.com/credits"}],"rate":{"limit":2500,"remaining":2270,"reset":1715299200},"results":[{"annotations":{"DMS":{"lat":"8\u00b0 58' 17.21748'' N","lng":"79\u00b0 32' 3.04872'' W"},"MGRS":"17PPK6114392017","Maidenhead":"FJ08fx53vd","Mercator":{"x":-8853704.441,"y":996144.589},"OSM":{"edit_url":"https://www.openstreetmap.org/edit?node=1242998122#map=17/8.97145/-79.53418","note_url":"https://www.openstreetmap.org/note/new#map=17/8.97145/-79.53418&layers=N","url":"https://www.openstreetmap.org/?mlat=8.97145&mlon=-79.53418#map=17/8.97145/-79.53418"},"UN_M49":{"regions":{"AMERICAS":"019","CENTRAL_AMERICA":"013","LATIN_AMERICA":"419","PA":"591","WORLD":"001"},"statistical_groupings":["LEDC"]},"callingcode":507,"currency":{"alternate_symbols":["US$"],"decimal_mark":".","disambiguate_symbol":"US$","html_entity":"$","iso_code":"USD","iso_numeric":"840","name":"United States Dollar","smallest_denomination":1,"subunit":"Cent","subunit_to_unit":100,"symbol":"$","symbol_first":1,"thousands_separator":","},"flag":"\ud83c\uddf5\ud83c\udde6","geohash":"d1x7n1hyrr2ges6zzwxx","qibla":61.97,"roadinfo":{"drive_on":"right","speed_in":"km/h"},"sun":{"rise":{"apparent":1715252460,"astronomical":1715248020,"civil":1715251140,"nautical":1715249580},"set":{"apparent":1715297340,"astronomical":1715215320,"civil":1715298660,"nautical":1715213760}},"timezone":{"name":"America/Panama","now_in_dst":0,"offset_sec":-18000,"offset_string":"-0500","short_name":"EST"},"what3words":{"words":"trails.wash.boomed"},"wikidata":"Q3306"},"bounds":{"northeast":{"lat":9.1314493,"lng":-79.3741802},"southwest":{"lat":8.8114493,"lng":-79.6941802}},"components":{"ISO_3166-1_alpha-2":"PA","ISO_3166-1_alpha-3":"PAN","ISO_3166-2":["PA-8"],"_category":"place","_normalized_city":"Panama","_type":"city","city":"Panama","continent":"South America","country":"Panama","country_code":"pa","county":"Distrito Panam\u00e1","postcode":"0843","state":"Panam\u00e1"},"confidence":3,"formatted":"Panama City, Distrito Panam\u00e1, Panama","geometry":{"lat":8.9714493,"lng":-79.5341802}},{"annotations":{"DMS":{"lat":"8\u00b0 33' 34.41240'' N","lng":"81\u00b0 7' 51.03624'' W"},"MGRS":"17PMK8560146161","Maidenhead":"EJ98kn44hh","Mercator":{"x":-9031444.175,"y":950054.615},"OSM":{"edit_url":"https://www.openstreetmap.org/edit?relation=287668#map=17/8.55956/-81.13084","note_url":"https://www.openstreetmap.org/note/new#map=17/8.55956/-81.13084&layers=N","url":"https://www.openstreetmap.org/?mlat=8.55956&mlon=-81.13084#map=17/8.55956/-81.13084"},"UN_M49":{"regions":{"AMERICAS":"019","CENTRAL_AMERICA":"013","LATIN_AMERICA":"419","PA":"591","WORLD":"001"},"statistical_groupings":["LEDC"]},"callingcode":507,"currency":{"alternate_symbols":["US$"],"decimal_mark":".","disambiguate_symbol":"US$","html_entity":"$","iso_code":"USD","iso_numeric":"840","name":"United States Dollar","smallest_denomination":1,"subunit":"Cent","subunit_to_unit":100,"symbol":"$","symbol_first":1,"thousands_separator":","},"flag":"\ud83c\uddf5\ud83c\udde6","geohash":"d1w29y4r436qr9mr5q0j","qibla":61.56,"roadinfo":{"drive_on":"right","speed_in":"km/h"},"sun":{"rise":{"apparent":1715252820,"astronomical":1715248440,"civil":1715251560,"nautical":1715250000},"set":{"apparent":1715297640,"astronomical":1715215680,"civil":1715298960,"nautical":1715214120}},"timezone":{"name":"America/Panama","now_in_dst":0,"offset_sec":-18000,"offset_string":"-0500","short_name":"EST"},"what3words":{"words":"clearcut.tonalities.blink"},"wikidata":"Q804"},"bounds":{"northeast":{"lat":9.8469028,"lng":-77.1585751},"southwest":{"lat":7.0027171,"lng":-83.0517245}},"components":{"ISO_3166-1_alpha-2":"PA","ISO_3166-1_alpha-3":"PAN","_category":"place","_type":"country","continent":"North America","country":"Panama","country_code":"pa"},"confidence":1,"formatted":"Panama","geometry":{"lat":8.559559,"lng":-81.1308434}},{"annotations":{"DMS":{"lat":"8\u00b0 11' 47.53176'' N","lng":"79\u00b0 11' 15.84096'' W"},"MGRS":"17PPK9964506475","Maidenhead":"FJ08je77le","Mercator":{"x":-8815138.187,"y":909474.842},"OSM":{"edit_url":"https://www.openstreetmap.org/edit?relation=5740665#map=17/8.19654/-79.18773","note_url":"https://www.openstreetmap.org/note/new#map=17/8.19654/-79.18773&layers=N","url":"https://www.openstreetmap.org/?mlat=8.19654&mlon=-79.18773#map=17/8.19654/-79.18773"},"UN_M49":{"regions":{"AMERICAS":"019","CENTRAL_AMERICA":"013","LATIN_AMERICA":"419","PA":"591","WORLD":"001"},"statistical_groupings":["LEDC"]},"callingcode":507,"currency":{"alternate_symbols":["US$"],"decimal_mark":".","disambiguate_symbol":"US$","html_entity":"$","iso_code":"USD","iso_numeric":"840","name":"United States Dollar","smallest_denomination":1,"subunit":"Cent","subunit_to_unit":100,"symbol":"$","symbol_first":1,"thousands_separator":","},"flag":"\ud83c\uddf5\ud83c\udde6","geohash":"d1rwwh1k214jk6ecdzrh","qibla":62.38,"roadinfo":{"drive_on":"right","speed_in":"km/h"},"sun":{"rise":{"apparent":1715252400,"astronomical":1715248020,"civil":1715251080,"nautical":1715249580},"set":{"apparent":1715297160,"astronomical":1715215200,"civil":1715298480,"nautical":1715213640}},"timezone":{"name":"America/Panama","now_in_dst":0,"offset_sec":-18000,"offset_string":"-0500","short_name":"EST"},"what3words":{"words":"surely.clustering.vetoed"},"wikidata":"Q557506"},"bounds":{"northeast":{"lat":9.5012171,"lng":-78.0607266},"southwest":{"lat":7.0109413,"lng":-79.919136}},"components":{"ISO_3166-1_alpha-2":"PA","ISO_3166-1_alpha-3":"PAN","ISO_3166-2":["PA-8"],"_category":"place","_type":"state","continent":"South America","country":"Panama","country_code":"pa","state":"Panam\u00e1"},"confidence":1,"formatted":"Panam\u00e1, Panama","geometry":{"lat":8.1965366,"lng":-79.1877336}},{"annotations":{"DMS":{"lat":"9\u00b0 12' 14.72904'' N","lng":"79\u00b0 24' 18.17928'' W"},"MGRS":"17PPL7522917806","Maidenhead":"FJ09he18jx","Mercator":{"x":-8839329.711,"y":1022200.204},"OSM":{"edit_url":"https://www.openstreetmap.org/edit?relation=8415626#map=17/9.20409/-79.40505","note_url":"https://www.openstreetmap.org/note/new#map=17/9.20409/-79.40505&layers=N","url":"https://www.openstreetmap.org/?mlat=9.20409&mlon=-79.40505#map=17/9.20409/-79.40505"},"UN_M49":{"regions":{"AMERICAS":"019","CENTRAL_AMERICA":"013","LATIN_AMERICA":"419","PA":"591","WORLD":"001"},"statistical_groupings":["LEDC"]},"callingcode":507,"currency":{"alternate_symbols":["US$"],"decimal_mark":".","disambiguate_symbol":"US$","html_entity":"$","iso_code":"USD","iso_numeric":"840","name":"United States Dollar","smallest_denomination":1,"subunit":"Cent","subunit_to_unit":100,"symbol":"$","symbol_first":1,"thousands_separator":","},"flag":"\ud83c\uddf5\ud83c\udde6","geohash":"d1xs35e18pp2nevggtur","qibla":61.93,"roadinfo":{"drive_on":"right","speed_in":"km/h"},"sun":{"rise":{"apparent":1715252400,"astronomical":1715247960,"civil":1715251080,"nautical":1715249520},"set":{"apparent":1715297280,"astronomical":1715215320,"civil":1715298600,"nautical":1715213760}},"timezone":{"name":"America/Panama","now_in_dst":0,"offset_sec":-18000,"offset_string":"-0500","short_name":"EST"},"what3words":{"words":"prodded.opportune.spring"}},"bounds":{"northeast":{"lat":9.5012171,"lng":-79.1249462},"southwest":{"lat":8.902583,"lng":-79.6976957}},"components":{"ISO_3166-1_alpha-2":"PA","ISO_3166-1_alpha-3":"PAN","ISO_3166-2":["PA-8"],"_category":"place","_type":"county","continent":"South America","country":"Panama","country_code":"pa","county":"Distrito Panam\u00e1","state":"Panam\u00e1"},"confidence":1,"formatted":"Distrito Panam\u00e1, Panama","geometry":{"lat":9.2040914,"lng":-79.4050498}}],"status":{"code":200,"message":"OK"},"stay_informed":{"blog":"https://blog.opencagedata.com","mastodon":"https://en.osm.town/@opencage"},"thanks":"For using an OpenCage API","timestamp":{"created_http":"Thu, 09 May 2024 16:02:49 GMT","created_unix":1715270569},"total_results":4}