{"documentation":"https://opencagedata.com/api","licenses":[{"name":"see attribution guide","url":"https://opencagedata.com/credits"}],"rate":{"limit":2500,"remaining":2200,"reset":1715299200},"results":[{"annotations":{"DMS":{"lat":"16\u00b0 31' 31.82484'' S","lng":"168\u00b0 6' 24.89544'' E"},"MGRS":"59KJB9117570715","Maidenhead":"RH43bl23tv","Mercator":{"x":18713576.221,"y":-1853513.221},"OSM":{"edit_url":"https://www.openstreetmap.org/edit?relation=2177246#map=17/-16.52551/168.10692","note_url":"https://www.openstreetmap.org/note/new#map=17/-16.52551/168.10692&layers=N","url":"https://www.openstreetmap.org/?mlat=-16.52551&mlon=168.10692#map=17/-16.52551/168.10692"},"UN_M49":{"regions":{"MELANESIA":"054","OCEANIA":"009","VU":"548","WORLD":"001"},"statistical_groupings":["LDC","LEDC","SIDS"]},"callingcode":678,"currency":{"alternate_symbols":[],"decimal_mark":".","html_entity":"","iso_code":"VUV","iso_numeric":"548","name":"Vanuatu Vatu","smallest_denomination":1,"subunit_to_unit":1,"symbol":"Vt","symbol_first":1,"thousands_separator":","},"flag":"\ud83c\uddfb\ud83c\uddfa","geohash":"rtp9creezn1re9xckf1z","qibla":284.29,"roadinfo":{"drive_on":"right","speed_in":"km/h"},"sun":{"rise":{"apparent":1715281320,"astronomical":1715276880,"civil":1715280000,"nautical":1715278440},"set":{"apparent":1715235900,"astronomical":1715240400,"civil":1715237280,"nautical":1715238840}},"timezone":{"name":"Pacific/Efate","now_in_dst":0,"offset_sec":39600,"offset_string":"+1100","short_name":"+11"},"what3words":{"words":"radicalism.overalls.stay"},"wikidata":"Q686"},"bounds":{"northeast":{"lat":-12.8713777,"lng":170.449982},"southwest":{"lat":-20.4627425,"lng":166.3355255}},"components":{"ISO_3166-1_alpha-2":"VU","ISO_3166-1_alpha-3":"VUT","_category":"place","_type":"country","continent":"Oceania","country":"Vanuatu","country_code":"vu"},"confidence":1,"formatted":"Vanuatu","geometry":{"lat":-16.5255069,"lng":168.1069154}}],"status":{"code":200,"message":"OK"},"stay_informed":{"blog":"https://blog.opencagedata.com","mastodon":"https://en.osm.town/@opencage"},"thanks":"For using an OpenCage API","timestamp":{"created_http":"Thu, 09 May 2024 16:05:04 GMT","created_unix":1715270704},"total_results":1}